{"data":{"ModuleTitle":{"label":"Module Title","value":"Company Description"},"CompanyName":{"label":"Company Name","value":"Thermo Fisher Scientific Inc"},"Symbol":{"label":"Symbol","value":"TMO"},"Address":{"label":"Address","value":"168 THIRD AVENUE, WALTHAM, Massachusetts, 02451, United States"},"Phone":{"label":"Phone","value":"+1 781 622-1000"},"Industry":{"label":"Industry","value":"Industrial Machinery/Components"},"Sector":{"label":"Sector","value":"Industrials"},"Region":{"label":"Region","value":"North America"},"CompanyDescription":{"label":"Company Description","value":"Thermo Fisher Scientific sells scientific instruments and laboratory equipment, diagnostics consumables, life science reagents and provides drug testing and manufacturing services. The firm operates through four segments (revenue figures include some cross-segment revenue and adjustments are made for the PPD acquisition and the deceleration of COVID-19 testing revenue): analytical technologies (15% of sales); specialty diagnostic products (14%); life science solutions (27%); and lab products and services (52%)."},"CompanyUrl":{"label":"Company Url","value":"https://www.thermofisher.com"},"KeyExecutives":{"label":"Key Executives","value":[{"name":"Alan B. Sachs","title":"Chief Medical Officer"},{"name":"Karen E. Nelson","title":"Chief Scientific Officer"},{"name":"Marc N. Casper","title":"Chairman, President & Chief Executive Officer"},{"name":"Michel Lagarde","title":"Chief Operating Officer & Executive Vice President"},{"name":"Ryan Snyder","title":"Chief Information Officer & Senior Vice President"},{"name":"Sebastian Pacios","title":"Senior Vice President-Clinical Research"}]}},"message":null,"status":{"rCode":200,"bCodeMessage":null,"developerMessage":null}}