{"data":{"ModuleTitle":{"label":"Module Title","value":"Company Description"},"CompanyName":{"label":"Company Name","value":"United Community Banks, Inc."},"Symbol":{"label":"Symbol","value":"UCB"},"Address":{"label":"Address","value":"125 HIGHWAY 515 EAST, BLAIRSVILLE, Georgia, 30512, United States"},"Phone":{"label":"Phone","value":"+1 706 781-2265"},"Industry":{"label":"Industry","value":"Major Banks"},"Sector":{"label":"Sector","value":"Finance"},"Region":{"label":"Region","value":"North America"},"CompanyDescription":{"label":"Company Description","value":"United Community Banks Inc is a bank holding company that operates through its wholly-owned subsidiary, Union Community Bank. The bank has scores of offices throughout portions of Georgia, Tennessee, and the Carolinas. It has traditionally grown through the organic growth of existing offices and de novo locations, complemented by selective acquisitions. United conducts substantially all of its operations through a community-focused operating model of separate community banks. The community banks offer a full range of retail and corporate banking services, including checking, savings, and time deposit accounts, as well as secured and unsecured loans, wire transfers, brokerage services, and other financial services. The bank's loan portfolio is well-diversified but predominantly commercial."},"CompanyUrl":{"label":"Company Url","value":"https://www.ucbi.com"},"KeyExecutives":{"label":"Key Executives","value":[{"name":"Herbert Lynn Harton","title":"Chairman, President & Chief Executive Officer"},{"name":"Mark Terry","title":"Chief Information Officer"}]}},"message":null,"status":{"rCode":200,"bCodeMessage":null,"developerMessage":null}}