{"data":{"ModuleTitle":{"label":"Module Title","value":"Company Description"},"CompanyName":{"label":"Company Name","value":"UNITIL Corporation"},"Symbol":{"label":"Symbol","value":"UTL"},"Address":{"label":"Address","value":"6 LIBERTY LANE WEST, HAMPTON, New Hampshire, 03842-1720, United States"},"Phone":{"label":"Phone","value":"+1 603 772-0775"},"Industry":{"label":"Industry","value":"Power Generation"},"Sector":{"label":"Sector","value":"Utilities"},"Region":{"label":"Region","value":"North America"},"CompanyDescription":{"label":"Company Description","value":"Unitil Corp is a holding company, through its subsidiaries it is engaged in the local distribution of electricity and natural gas throughout its service territories in the states of New Hampshire, Massachusetts, and Maine. It reports three segments namely utility gas operations, utility electric operations, and non-regulated."},"CompanyUrl":{"label":"Company Url","value":"https://www.unitil.com"},"KeyExecutives":{"label":"Key Executives","value":[{"name":"Justin Eisfeller","title":"Chief Technology Officer & Vice President"},{"name":"Thomas P. Meissner","title":"Chairman & Chief Executive Officer"}]}},"message":null,"status":{"rCode":200,"bCodeMessage":null,"developerMessage":null}}