{"data":{"ModuleTitle":{"label":"Module Title","value":"Company Description"},"CompanyName":{"label":"Company Name","value":"Vishay Intertechnology, Inc."},"Symbol":{"label":"Symbol","value":"VSH"},"Address":{"label":"Address","value":"63 LANCASTER AVENUE, MALVERN, Pennsylvania, 19355-2143, United States"},"Phone":{"label":"Phone","value":"+1 610 644-1300"},"Industry":{"label":"Industry","value":"Electrical Products"},"Sector":{"label":"Sector","value":"Technology"},"Region":{"label":"Region","value":"North America"},"CompanyDescription":{"label":"Company Description","value":"Vishay Intertechnology Inc provides a broad product portfolio of discrete semiconductors and passive electronic components to original equipment manufacturers and distributors. These products are found in industrial, computing, automotive, consumer, telecommunications, power supplies, military, aerospace, and medical markets and serve customer worldwide. Its product segments consist of two general classes: semiconductors and passive components. The company's operating segment includes metal oxide semiconductor field-effect transistors, diodes, optoelectronic components, resistors, inductors, and capacitors. Revenue mainly comes from resistors, which are basic components used in all forms of electronic circuitry to adjust and regulate levels of voltage and current."},"CompanyUrl":{"label":"Company Url","value":"https://www.vishay.com"},"KeyExecutives":{"label":"Key Executives","value":[{"name":"Jeff Webster","title":"Chief Operating Officer"},{"name":"Joel J. Smejkal","title":"President, Chief Executive Officer & Director"},{"name":"Roy Shoshani","title":"Chief Technical Officer & Executive Vice President"}]}},"message":null,"status":{"rCode":200,"bCodeMessage":null,"developerMessage":null}}