{"data":{"ModuleTitle":{"label":"Module Title","value":"Company Description"},"CompanyName":{"label":"Company Name","value":"Bogota Financial Corp."},"Symbol":{"label":"Symbol","value":"BSBK"},"Address":{"label":"Address","value":"819 TEANECK ROAD,TEANECK, NEW JERSEY, New Jersey, 07666, United States"},"Phone":{"label":"Phone","value":"+1 201 862-0660"},"Industry":{"label":"Industry","value":"Banks"},"Sector":{"label":"Sector","value":"Finance"},"Region":{"label":"Region","value":"North America"},"CompanyDescription":{"label":"Company Description","value":"Bogota Financial Corp is a New Jersey-based bank. It offers personal and business banking services such as savings, certificates of deposits, online banking, loans, and many more. The Bank generally grants residential, commercial, and consumer loans to, and accepts deposits from, customers in New Jersey."},"CompanyUrl":{"label":"Company Url","value":"https://www.bogotasavingsbank.com"},"KeyExecutives":{"label":"Key Executives","value":[{"name":"Kevin Pace","title":"President, Chief Executive Officer & Director"}]}},"message":null,"status":{"rCode":200,"bCodeMessage":null,"developerMessage":null}}