{"data":{"ModuleTitle":{"label":"Module Title","value":"Company Description"},"CompanyName":{"label":"Company Name","value":"Badger Meter, Inc."},"Symbol":{"label":"Symbol","value":"BMI"},"Address":{"label":"Address","value":"4545 W. BROWN DEER ROAD, MILWAUKEE, Wisconsin, 53233, United States"},"Phone":{"label":"Phone","value":"+1 414 355-0400"},"Industry":{"label":"Industry","value":"Industrial Machinery/Components"},"Sector":{"label":"Sector","value":"Industrials"},"Region":{"label":"Region","value":"North America"},"CompanyDescription":{"label":"Company Description","value":"Badger Meter Inc is a manufacturer and marketer of products incorporating flow measurement, control and communication solutions. The company's products measure water, oil, chemicals and other fluids, provide and communicate timely measurement data. Badger's product lines include two categories: sales of water meters and related technologies to municipal water utilities (municipal water), and sales of meters to various industries for water and other fluids (flow instrumentation). It derives most of its revenues from the United States."},"CompanyUrl":{"label":"Company Url","value":"https://www.badgermeter.com"},"KeyExecutives":{"label":"Key Executives","value":[{"name":"Fred J. Begale","title":"Vice President-Engineering"},{"name":"Kenneth C. Bockhorst","title":"Chairman, President & Chief Executive Officer"},{"name":"Richard Htwe","title":"Vice President-Global Operations"}]}},"message":null,"status":{"rCode":200,"bCodeMessage":null,"developerMessage":null}}