{"data":{"ModuleTitle":{"label":"Module Title","value":"Company Description"},"CompanyName":{"label":"Company Name","value":"iPower Inc."},"Symbol":{"label":"Symbol","value":"IPW"},"Address":{"label":"Address","value":"2399 BATEMAN AVENUE, DUARTE, California, 91010, United States"},"Phone":{"label":"Phone","value":"+1 626 863-7344"},"Industry":{"label":"Industry","value":"RETAIL: Building Materials"},"Sector":{"label":"Sector","value":"Consumer Discretionary"},"Region":{"label":"Region","value":"North America"},"CompanyDescription":{"label":"Company Description","value":"iPower Inc is a online hydroponic equipment and accessory retailer and supplier in North America. The company sells the products through own website as well as online channel partners that include Amazon, Walmart and eBay."},"CompanyUrl":{"label":"Company Url","value":"https://www.meetipower.com"},"KeyExecutives":{"label":"Key Executives","value":[{"name":"Chen Long Tan","title":"Chairman, President & Chief Executive Officer"}]}},"message":null,"status":{"rCode":200,"bCodeMessage":null,"developerMessage":null}}