{"data":{"ModuleTitle":{"label":"Module Title","value":"Company Description"},"CompanyName":{"label":"Company Name","value":"Tungray Technologies Inc"},"Symbol":{"label":"Symbol","value":"TRSG"},"Address":{"label":"Address","value":"`, Singapore"},"Phone":{"label":"Phone","value":"+65 6636 9820"},"Industry":{"label":"Industry","value":"Industrial Machinery/Components"},"Sector":{"label":"Sector","value":"Industrials"},"Region":{"label":"Region","value":"Asia"},"CompanyDescription":{"label":"Company Description","value":"Tungray Technologies Inc. is an engineer-to-order (ETO) company. The Company provides customized industrial manufacturing solutions to Original Equipment Manufacturers (OEMs) in the semiconductors, printers, electronics, and home appliances sectors. Its three business lines consist of customized industrial manufacturing solutions, direct drive and linear direct current (DC) motors and induction welding equipment manufacturing. Its Singapore subsidiaries provides research, development and assembling of solution prototypes, while the China subsidiary provides manufacturing support for necessary component production or delivers certain high-volume solution manufacturing purchases."},"CompanyUrl":{"label":"Company Url","value":"https://www.tungray.tech"},"KeyExecutives":{"label":"Key Executives","value":[{"name":"Lei Yao","title":"Chief Technology Officer"},{"name":"Wanjun Yao","title":"Chairman & Chief Executive Officer"}]}},"message":null,"status":{"rCode":200,"bCodeMessage":null,"developerMessage":null}}