{"data":{"ModuleTitle":{"label":"Module Title","value":"Company Description"},"CompanyName":{"label":"Company Name","value":"VS Media Holdings Limited"},"Symbol":{"label":"Symbol","value":"VSME"},"Address":{"label":"Address","value":"China"},"Phone":{"label":"Phone","value":"+852 2889 1313"},"Industry":{"label":"Industry","value":"Publishing"},"Sector":{"label":"Sector","value":"Consumer Discretionary"},"Region":{"label":"Region","value":"Asia"},"CompanyDescription":{"label":"Company Description","value":"VS MEDIA Holdings Limited, an investment holding company, operates a network of digital creators who create and upload content to social media platforms, such as Facebook, YouTube, Instagram, and TikTok."},"CompanyUrl":{"label":"Company Url","value":"https://www.vs-media.com"},"KeyExecutives":{"label":"Key Executives","value":[{"name":"Nga Fan Wong","title":"Chairman & Chief Executive Officer"}]}},"message":null,"status":{"rCode":200,"bCodeMessage":null,"developerMessage":null}}