{"data":{"ModuleTitle":{"label":"Module Title","value":"Company Description"},"CompanyName":{"label":"Company Name","value":"Global Self Storage, Inc."},"Symbol":{"label":"Symbol","value":"SELF"},"Address":{"label":"Address","value":"3814 ROUTE 44,MILLBROOK, NEW YORK, New York, 12545, United States"},"Phone":{"label":"Phone","value":"+1 212 785-0900"},"Industry":{"label":"Industry","value":"Real Estate Investment Trusts"},"Sector":{"label":"Sector","value":"Real Estate"},"Region":{"label":"Region","value":"North America"},"CompanyDescription":{"label":"Company Description","value":"Global Self Storage Inc is a self-administered and self-managed REIT that owns, operates, manages, acquires, develops and redevelops self-storage properties. The company's self-storage properties are designed to offer affordable, easily accessible and secure storage space for residential and commercial customers. Through its wholly-owned subsidiaries, the company owns and/or manages close to 13 self-storage properties in Connecticut, Illinois, Indiana, New York, Ohio, Pennsylvania, South Carolina, and Oklahoma."},"CompanyUrl":{"label":"Company Url","value":"https://www.globalselfstorage.us"},"KeyExecutives":{"label":"Key Executives","value":[{"name":"Donald Klimoski","title":"Secretary, Chief Compliance Officer & SVP"},{"name":"Mark Campbell Winmill","title":"Chairman, President & Chief Executive Officer"}]}},"message":null,"status":{"rCode":200,"bCodeMessage":null,"developerMessage":null}}