{"data":{"ModuleTitle":{"label":"Module Title","value":"Company Description"},"CompanyName":{"label":"Company Name","value":"SkyWater Technology, Inc."},"Symbol":{"label":"Symbol","value":"SKYT"},"Address":{"label":"Address","value":"2401 EAST 86TH STREET, BLOOMINGTON, Minnesota, 55425, United States"},"Phone":{"label":"Phone","value":"+1 952 851-5200"},"Industry":{"label":"Industry","value":"Semiconductors"},"Sector":{"label":"Sector","value":"Technology"},"Region":{"label":"Region","value":"North America"},"CompanyDescription":{"label":"Company Description","value":"SkyWater Technology Inc is a pure-play technology foundry that offers advanced semiconductor development and manufacturing services from its fabrication facility, in Minnesota and advanced packaging services from the Florida facility. It specializes in advanced Innovation Engineering Services and volume manufacturing of a wide variety of differentiated integrated circuits."},"CompanyUrl":{"label":"Company Url","value":"https://www.skywatertechnology.com"},"KeyExecutives":{"label":"Key Executives","value":[{"name":"John Sakamoto","title":"President & Chief Operating Officer"},{"name":"Sudhakar Adivikolanu","title":"Senior VP-Supply Chain & Information Technology"},{"name":"Thomas J. Sonderman","title":"Chief Executive Officer & Director"}]}},"message":null,"status":{"rCode":200,"bCodeMessage":null,"developerMessage":null}}