{"data":{"ModuleTitle":{"label":"Module Title","value":"Company Description"},"CompanyName":{"label":"Company Name","value":"Qurate Retail, Inc."},"Symbol":{"label":"Symbol","value":"QRTEA"},"Address":{"label":"Address","value":"12300 LIBERTY BOULEVARD, ENGLEWOOD, Colorado, 80112, United States"},"Phone":{"label":"Phone","value":"+1 720 875-5300"},"Industry":{"label":"Industry","value":"Catalog/Specialty Distribution"},"Sector":{"label":"Sector","value":"Consumer Discretionary"},"Region":{"label":"Region","value":"North America"},"CompanyDescription":{"label":"Company Description","value":"Qurate Retail Inc, through its subsidiaries, is engaged in the video and online commerce industries. Its segments include QxH, which includes QVC U.S. and HSN market and sell a wide variety of consumer products in the United States, primarily using their televised shopping programs and via the Internet through their websites and mobile applications; QVC International segment markets and sells a wide variety of consumer products in several foreign countries, primarily using its televised shopping programs and via the Internet through its international websites and mobile applications; and Zulily markets and sells a wide variety of consumer products in the United States and several foreign countries. Its geographical segments include the United States, Japan, Germany, and Other countries."},"CompanyUrl":{"label":"Company Url","value":"https://www.qurateretail.com"},"KeyExecutives":{"label":"Key Executives","value":[{"name":"David L. Rawlinson","title":"President, Chief Executive Officer & Director"}]}},"message":null,"status":{"rCode":200,"bCodeMessage":null,"developerMessage":null}}