{"data":{"ModuleTitle":{"label":"Module Title","value":"Company Description"},"CompanyName":{"label":"Company Name","value":"CarGurus, Inc."},"Symbol":{"label":"Symbol","value":"CARG"},"Address":{"label":"Address","value":"2 CANAL PARK,4TH FLOOR, CAMBRIDGE, Massachusetts, 02141, United States"},"Phone":{"label":"Phone","value":"+1 617 354-0068"},"Industry":{"label":"Industry","value":"EDP Services"},"Sector":{"label":"Sector","value":"Technology"},"Region":{"label":"Region","value":"North America"},"CompanyDescription":{"label":"Company Description","value":"CarGurus Inc is a company that acts as an online automotive marketplace connecting buyers and sellers of new and used cars. The company provides three types of marketplace Listing products, Restricted Listings, and Enhanced or Featured Listing through which it offers real-time and historical data analyzing the connections and pricing analysis. It also provides all dealers with a web widget to place Deal Rating Badges, which show deal rating. The listing platforms offer auto manufacturers and others to buy advertising on the company's site and target consumers based on the make, model, and zip code of the cars. The company operates through two geographical segments namely United States and the International. Most of the company's revenue comes from the United States."},"CompanyUrl":{"label":"Company Url","value":"https://www.cargurus.com"},"KeyExecutives":{"label":"Key Executives","value":[{"name":"Jason Trevisan","title":"Chief Executive Officer & Director"},{"name":"Matthew Quinn","title":"Chief Technology Officer"},{"name":"Samuel Zales","title":"President & Chief Operating Officer"}]}},"message":null,"status":{"rCode":200,"bCodeMessage":null,"developerMessage":null}}