{"data":{"ModuleTitle":{"label":"Module Title","value":"Company Description"},"CompanyName":{"label":"Company Name","value":"Carver Bancorp, Inc."},"Symbol":{"label":"Symbol","value":"CARV"},"Address":{"label":"Address","value":"75 WEST 125TH STREET, NEW YORK, New York, 10027, United States"},"Phone":{"label":"Phone","value":"+1 718 230-2900"},"Industry":{"label":"Industry","value":"Savings Institutions"},"Sector":{"label":"Sector","value":"Finance"},"Region":{"label":"Region","value":"North America"},"CompanyDescription":{"label":"Company Description","value":"Carver Bancorp Inc is a holding company and conducts its business as a unitary saving and loan holding firm and the business of the company consists of the operation of its subsidiary. The bank offers a wide range of financial solutions to meet customers personal banking. It offers other consumer and commercial banking products and services, such as debit cards, online banking, online bill pay, and telephone banking. The company provides deposit products, such as demand, savings, and time deposits for consumers, businesses, and governmental and quasi-governmental agencies in its market area within New York City."},"CompanyUrl":{"label":"Company Url","value":"https://www.carverbank.com"},"KeyExecutives":{"label":"Key Executives","value":[{"name":"Donald Felix","title":"President & Chief Executive Officer"}]}},"message":null,"status":{"rCode":200,"bCodeMessage":null,"developerMessage":null}}