{"data":{"ModuleTitle":{"label":"Module Title","value":"Company Description"},"CompanyName":{"label":"Company Name","value":"Park-Ohio Holdings Corp."},"Symbol":{"label":"Symbol","value":"PKOH"},"Address":{"label":"Address","value":"6065 PARKLAND BOULEVARD, CLEVELAND, Ohio, 44124, United States"},"Phone":{"label":"Phone","value":"+1 440 947-2000"},"Industry":{"label":"Industry","value":"Industrial Specialties"},"Sector":{"label":"Sector","value":"Industrials"},"Region":{"label":"Region","value":"North America"},"CompanyDescription":{"label":"Company Description","value":"Park-Ohio Holdings Corp is a company, engaged in industrial supply chain logistics and diversified manufacturing business. It operates in three business segments namely Supply Technologies, Assembly Components and Engineered Products. Geographically, the business of the group is amplifying across the region of the United States, Asia, Europe, Canada, Mexico and others. The company derives most of the revenue from the Supply Technologies segment which provides the customer with total supply management services such as engineering and design support, supplier selection, quality assurance, barcoding, product packaging and tracking, just-in-time and point-of-use delivery and electronic billing services for a range of production components."},"CompanyUrl":{"label":"Company Url","value":"http://www.pkoh.com"},"KeyExecutives":{"label":"Key Executives","value":[{"name":"Matthew V. Crawford","title":"Chairman, President & Chief Executive Officer"}]}},"message":null,"status":{"rCode":200,"bCodeMessage":null,"developerMessage":null}}