{"data":{"ModuleTitle":{"label":"Module Title","value":"Company Description"},"CompanyName":{"label":"Company Name","value":"Network-1 Technologies, Inc."},"Symbol":{"label":"Symbol","value":"NTIP"},"Address":{"label":"Address","value":"65 LOCUST AVENUE,SUITE 912, NEW CANAAN, Connecticut, 06840, United States"},"Phone":{"label":"Phone","value":"+1 203 920-1055"},"Industry":{"label":"Industry","value":"Multi-Sector Companies"},"Sector":{"label":"Sector","value":"Miscellaneous"},"Region":{"label":"Region","value":"North America"},"CompanyDescription":{"label":"Company Description","value":"Network-1 Technologies Inc is involved in the business of the development, licensing, and protection of intellectual property rights. The company's patent portfolios include the remote power patent portfolio, the mirror worlds patent portfolio, the cos patent portfolio and the QoS patents. It derives its revenue from licensing of its intellectual property and related activities. The company's current strategy includes continuing to pursue licensing opportunities for its intellectual property assets."},"CompanyUrl":{"label":"Company Url","value":"https://www.network-1.com"},"KeyExecutives":{"label":"Key Executives","value":[{"name":"Corey M. Horowitz","title":"Chairman & Chief Executive Officer"}]}},"message":null,"status":{"rCode":200,"bCodeMessage":null,"developerMessage":null}}