{"data":{"ModuleTitle":{"label":"Module Title","value":"Company Description"},"CompanyName":{"label":"Company Name","value":"Eos Energy Enterprises, Inc."},"Symbol":{"label":"Symbol","value":"EOSE"},"Address":{"label":"Address","value":"3920 PARK AVENUE, EDISON, New Jersey, 08820, United States"},"Phone":{"label":"Phone","value":"+1 732 225-8400"},"Industry":{"label":"Industry","value":"Industrial Machinery/Components"},"Sector":{"label":"Sector","value":"Miscellaneous"},"Region":{"label":"Region","value":"North America"},"CompanyDescription":{"label":"Company Description","value":"Eos Energy Enterprises Inc designs, manufacture, and markets battery storage solutions for the electric utility industry. The solutions are used in the utility sector, the renewable energy sector, and the industrial sector. Its flagship product Eos Znyth is a stationary battery energy storage system."},"CompanyUrl":{"label":"Company Url","value":"https://www.eose.com"},"KeyExecutives":{"label":"Key Executives","value":[{"name":"Daniel Amezquita","title":"Chief Operating Officer"},{"name":"Francis Richey","title":"Chief Technology Officer"},{"name":"Joseph Mastrangelo","title":"President, Chief Executive Officer & Director"}]}},"message":null,"status":{"rCode":200,"bCodeMessage":null,"developerMessage":null}}