{"data":{"ModuleTitle":{"label":"Module Title","value":"Company Description"},"CompanyName":{"label":"Company Name","value":"Celanese Corporation"},"Symbol":{"label":"Symbol","value":"CE"},"Address":{"label":"Address","value":"222 WEST LAS COLINAS BOULEVARD,SUITE 900N, IRVING, Texas, 75039-5421, United States"},"Phone":{"label":"Phone","value":"+1 972 443-4000"},"Industry":{"label":"Industry","value":"Major Chemicals"},"Sector":{"label":"Sector","value":"Industrials"},"Region":{"label":"Region","value":"North America"},"CompanyDescription":{"label":"Company Description","value":"Celanese is one of the world's largest producers of acetic acid and its downstream derivative chemicals, which are used in various end markets, including coatings and adhesives. The company also produces specialty polymers used in the automotive, electronics, medical, and consumer end markets as well as cellulose derivatives used in cigarette filters."},"CompanyUrl":{"label":"Company Url","value":"https://www.celanese.com"},"KeyExecutives":{"label":"Key Executives","value":[{"name":"Lori J. Ryerkerk","title":"Chairman, President & Chief Executive Officer"},{"name":"Sameer Purao","title":"Chief Information Officer"},{"name":"Scott A. Richardson","title":"Chief Operating Officer & Executive Vice President"}]}},"message":null,"status":{"rCode":200,"bCodeMessage":null,"developerMessage":null}}