{"data":{"ModuleTitle":{"label":"Module Title","value":"Company Description"},"CompanyName":{"label":"Company Name","value":"Cousins Properties Incorporated"},"Symbol":{"label":"Symbol","value":"CUZ"},"Address":{"label":"Address","value":"3344 PEACHTREE ROAD NE,SUITE 1800, ATLANTA, Georgia, 30326-4802, United States"},"Phone":{"label":"Phone","value":"+1 404 407-1000"},"Industry":{"label":"Industry","value":"Real Estate Investment Trusts"},"Sector":{"label":"Sector","value":"Real Estate"},"Region":{"label":"Region","value":"North America"},"CompanyDescription":{"label":"Company Description","value":"Cousins Properties Inc is a real estate investment trust principally involved in the ownership, management, and development of properties in the Southern United States. Cousins Properties' real estate portfolio primarily comprises offices and mixed-use developments that encompass both apartment and retail space. Offices make up the vast majority of the portfolio in terms of total square footage. Cousins' assets are mainly located in Texas and Georgia, with North Carolina also playing host to a smaller amount of rental space. The company derives nearly all of its revenue in the form of rental income from its properties, most of which comes from its office locations. A diverse set of tenants in the cities of Houston and Atlanta represent the company's major markets."},"CompanyUrl":{"label":"Company Url","value":"https://www.cousins.com"},"KeyExecutives":{"label":"Key Executives","value":[{"name":"Brandon van Orden","title":"Chief Information Officer & Senior Vice President"},{"name":"J. Kennedy Hicks","title":"Chief Investment Officer, EVP & MD-Atlanta"},{"name":"M. Colin Connolly","title":"President, Chief Executive Officer & Director"},{"name":"Richard G. Hickson","title":"Executive Vice President-Operations"}]}},"message":null,"status":{"rCode":200,"bCodeMessage":null,"developerMessage":null}}