{"data":{"ModuleTitle":{"label":"Module Title","value":"Company Description"},"CompanyName":{"label":"Company Name","value":"Old Republic International Corporation"},"Symbol":{"label":"Symbol","value":"ORI"},"Address":{"label":"Address","value":"307 NORTH MICHIGAN AVENUE, CHICAGO, Illinois, 60601, United States"},"Phone":{"label":"Phone","value":"+1 312 346-8100"},"Industry":{"label":"Industry","value":"Property-Casualty Insurers"},"Sector":{"label":"Sector","value":"Finance"},"Region":{"label":"Region","value":"North America"},"CompanyDescription":{"label":"Company Description","value":"Old Republic International Corp offers a diverse range of specialized insurance products to individuals and institutions. It operates in three segments: General Insurance (property and liability insurance), Title Insurance, and Republic Financial Indemnity Group (RFIG) Run-off. General Insurance includes products such as Automobile Extended Warranty Insurance, Aviation, Commercial Automobile Insurance, Inland Marine, Travel Accident, Workers' Compensation, Financial Indemnity, and others. Title Insurance's business consists primarily of the issuance of policies to real estate purchasers and investors based upon searches of the public records which contain information concerning interests in real property. Almost all of its revenue is generated from the United States."},"CompanyUrl":{"label":"Company Url","value":"https://www.oldrepublic.com"},"KeyExecutives":{"label":"Key Executives","value":[{"name":"Craig R. Smiddy","title":"President, Chief Executive Officer & Director"},{"name":"Phillip A. Schutt","title":"Senior Vice President-Investments"}]}},"message":null,"status":{"rCode":200,"bCodeMessage":null,"developerMessage":null}}