{"data":{"ModuleTitle":{"label":"Module Title","value":"Company Description"},"CompanyName":{"label":"Company Name","value":"Rocky Brands, Inc."},"Symbol":{"label":"Symbol","value":"RCKY"},"Address":{"label":"Address","value":"39 EAST CANAL STREET, NELSONVILLE, Ohio, 45764, United States"},"Phone":{"label":"Phone","value":"+1 740 753-1951"},"Industry":{"label":"Industry","value":"Shoe Manufacturing"},"Sector":{"label":"Sector","value":"Consumer Discretionary"},"Region":{"label":"Region","value":"North America"},"CompanyDescription":{"label":"Company Description","value":"Rocky Brands Inc acts as a designer, manufacturer, and marketer of premium-quality footwear and apparel. The company's family of brands includes Rocky, Georgia Boot, Durango, Lehigh, Creative Recreation, and the licensed brand Michelin footwear. The company operates its business through three business segments: Wholesale, Retail and Contract. In its wholesale business, the company distributes products through a wide range of distribution channels representing over 10,000 retail store locations in the U.S. and Canada as well as in several international markets. The retail business includes direct sales of products to consumers through its e-commerce websites and Rocky outlet store. The Contract segment sells footwear under the Rocky brand to the U.S. military."},"CompanyUrl":{"label":"Company Url","value":"https://www.rockybrands.com"},"KeyExecutives":{"label":"Key Executives","value":[{"name":"Jason S. Brooks","title":"Chairman, President & Chief Executive Officer"},{"name":"Thomas D. Robertson","title":"Treasurer, Chief Operating & Financial Officer"}]}},"message":null,"status":{"rCode":200,"bCodeMessage":null,"developerMessage":null}}