{"data":{"ModuleTitle":{"label":"Module Title","value":"Company Description"},"CompanyName":{"label":"Company Name","value":"Imax Corporation"},"Symbol":{"label":"Symbol","value":"IMAX"},"Address":{"label":"Address","value":"2525 SPEAKMAN DRIVE, MISSISSAUGA, Ontario, L5K 1B1, Canada"},"Phone":{"label":"Phone","value":"+1 905 403-6500"},"Industry":{"label":"Industry","value":"Industrial Machinery/Components"},"Sector":{"label":"Sector","value":"Consumer Discretionary"},"Region":{"label":"Region","value":"North America"},"CompanyDescription":{"label":"Company Description","value":"Imax is now primarily a technology hardware and brand-licensing company that does not operate the vast majority of Imax theaters. Instead, the firm generates revenue via selling and leasing the required proprietary equipment and via fees for digitally remastering standard films into the proprietary Imax format. The firm has expanded from 210 commercial theaters in 2008 to over 1,650 today and increased the annual number of Imax releases from 13 in 2007 to 60 in 2019."},"CompanyUrl":{"label":"Company Url","value":"https://www.imax.com"},"KeyExecutives":{"label":"Key Executives","value":[{"name":"Pablo Calamera","title":"Chief Technology Officer & Executive VP"},{"name":"Richard Lewis Gelfond","title":"Chief Executive Officer & Director"}]}},"message":null,"status":{"rCode":200,"bCodeMessage":null,"developerMessage":null}}