{"data":{"ModuleTitle":{"label":"Module Title","value":"Company Description"},"CompanyName":{"label":"Company Name","value":"InvenTrust Properties Corp."},"Symbol":{"label":"Symbol","value":"IVT"},"Address":{"label":"Address","value":"3025 HIGHLAND PARKWAY,SUITE 350, DOWNERS GROVE, Illinois, 60515, United States"},"Phone":{"label":"Phone","value":"+1 855 377-0510"},"Industry":{"label":"Industry","value":"Real Estate Investment Trusts"},"Sector":{"label":"Sector","value":"Real Estate"},"Region":{"label":"Region","value":"North America"},"CompanyDescription":{"label":"Company Description","value":"InvenTrust Properties Corp is the United States of AmericaÃ,Â based company qualified as a REIT (Real Estate Investment Trust). It owns, manages, acquires and develops a diversified portfolio of commercial real estate located across the United States. The company also owns properties in development and partially owns properties through joint ventures, as well as investments in marketable securities and other assets. The company focuses on investing in an open-air retail platform comprised of grocery-anchored centers and necessity-based power centers. InvenTrust operates through a single segment i.e. multi-tenant retail."},"CompanyUrl":{"label":"Company Url","value":"https://www.inventrustproperties.com"},"KeyExecutives":{"label":"Key Executives","value":[{"name":"Christy L. David","title":"COO, Secretary, Executive VP & General Counsel"},{"name":"Daniel Joseph Busch","title":"President, Chief Executive Officer & Director"},{"name":"David Heimberger","title":"Chief Investment Officer"}]}},"message":null,"status":{"rCode":200,"bCodeMessage":null,"developerMessage":null}}