{"data":{"ModuleTitle":{"label":"Module Title","value":"Company Description"},"CompanyName":{"label":"Company Name","value":"Pioneer High Income Fund, Inc."},"Symbol":{"label":"Symbol","value":"PHT"},"Address":{"label":"Address","value":"United States"},"Phone":{"label":"Phone","value":""},"Industry":{"label":"Industry","value":"Investment Managers"},"Sector":{"label":"Sector","value":"Finance"},"Region":{"label":"Region","value":"North America"},"CompanyDescription":{"label":"Company Description","value":"Pioneer High Income Trust is a closed-end management investment company. Its investment objective is to provide high level of current income and to seek capital appreciation."},"CompanyUrl":{"label":"Company Url","value":"https://www.amundi.com"},"KeyExecutives":{"label":"Key Executives","value":[{"name":"Anthony J. Koenig","title":"COO, CFO, Treasurer, Chief Accounting Officer & MD"},{"name":"Lisa Marinello Jones","title":"President, Chief Executive Officer & Trustee"}]}},"message":null,"status":{"rCode":200,"bCodeMessage":null,"developerMessage":null}}