{"data":{"ModuleTitle":{"label":"Module Title","value":"Company Description"},"CompanyName":{"label":"Company Name","value":"Fresh Del Monte Produce, Inc."},"Symbol":{"label":"Symbol","value":"FDP"},"Address":{"label":"Address","value":"87 MARY STREET, GEORGE TOWN,C/O H&C CORPORATE SERVICES LTD P.O. BOX 698, 4TH FLOOR, APOLLO HOUSE, GRAND CAYMAN, KY1-1107, Cayman Islands"},"Phone":{"label":"Phone","value":"+1 305 520-8400"},"Industry":{"label":"Industry","value":"Farming/Seeds/Milling"},"Sector":{"label":"Sector","value":"Consumer Staples"},"Region":{"label":"Region","value":"Caribbean"},"CompanyDescription":{"label":"Company Description","value":"Fresh Del Monte Produce Inc produces, markets, and distributes fresh fruit and vegetables internationally. Additionally, it prepares and distributes juices, beverages, and snacks. The products are shipped to retail stores, foodservice operators, wholesalers, and other distributors. The company owns a trucking company and uses asset-based carriers to deliver by land, and utilizes its fleet of ships mixed with chartered refrigerated vessels to deliver by sea. Fresh Del Monte Produce incorporates a worldwide salesforce to conduct selling and marketing, and has strategically constructed distribution centers around the world to deliver its products. It operates in three segments: Fresh and value-added products; Bananas: and Other products and services."},"CompanyUrl":{"label":"Company Url","value":"https://www.freshdelmonte.com"},"KeyExecutives":{"label":"Key Executives","value":[{"name":"Hans Sauter","title":"Chief Sustainability Officer & Senior VP"},{"name":"Mohammad Ahmad Mohammad Abu-Ghazaleh","title":"Chairman & Chief Executive Officer"},{"name":"Mohammed Abbas","title":"Chief Operating Officer & Executive Vice President"},{"name":"Murtaza Habib","title":"Vice President-Information Technology"}]}},"message":null,"status":{"rCode":200,"bCodeMessage":null,"developerMessage":null}}