{"data":{"ModuleTitle":{"label":"Module Title","value":"Company Description"},"CompanyName":{"label":"Company Name","value":"fuboTV Inc."},"Symbol":{"label":"Symbol","value":"FUBO"},"Address":{"label":"Address","value":"1290 AVENUE OF THE AMERICAS, NEW YORK, New York, 10104, United States"},"Phone":{"label":"Phone","value":"+1 212 672-0055"},"Industry":{"label":"Industry","value":"Movies/Entertainment"},"Sector":{"label":"Sector","value":"Consumer Discretionary"},"Region":{"label":"Region","value":"North America"},"CompanyDescription":{"label":"Company Description","value":"FuboTV Inc is a sports-first, live TV streaming company, offering subscribers access to tens of thousands of live sporting events annually as well as news and entertainment content. Its platform, fuboTV, allows customers to access content through streaming devices and on SmartTVs, mobile phones, tablets, and computers. The company offer subscribers a live TV streaming service with the option to purchase incremental features available for purchase that include additional content or enhanced functionality best suited to their preferences. The operating segments of the group are Streaming and Online wagering, of which a majority of revenue is derived from the Streaming segment. It has a business presence in the U.S. and other international countries."},"CompanyUrl":{"label":"Company Url","value":"https://www.fubo.tv"},"KeyExecutives":{"label":"Key Executives","value":[{"name":"Alberto Horihuela Suarez","title":"Chief Operating Officer"},{"name":"David Gandler","title":"Chief Executive Officer & Director"}]}},"message":null,"status":{"rCode":200,"bCodeMessage":null,"developerMessage":null}}