{"data":{"ModuleTitle":{"label":"Module Title","value":"Company Description"},"CompanyName":{"label":"Company Name","value":"Elevance Health, Inc."},"Symbol":{"label":"Symbol","value":"ELV"},"Address":{"label":"Address","value":"220 VIRGINIA AVENUE, INDIANAPOLIS, Indiana, 46204, United States"},"Phone":{"label":"Phone","value":"+1 800 331-1476"},"Industry":{"label":"Industry","value":"Medical Specialities"},"Sector":{"label":"Sector","value":"Health Care"},"Region":{"label":"Region","value":"North America"},"CompanyDescription":{"label":"Company Description","value":"Elevance Health (formerly known as Anthem) remains one of the leading health insurers in the U.S., providing medical benefits to roughly 45 million medical members. The company offers employer, individual, and government-sponsored coverage plans. Elevance differs from its peers in its unique position as the largest single provider of Blue Cross Blue Shield branded coverage, operating as the licensee for the Blue Cross Blue Shield Association in 14 states. Through acquisitions, such as the Amerigroup deal in 2012 and MMM in 2021, Elevance's reach expands beyond those states through government-sponsored programs such as Medicaid, too."},"CompanyUrl":{"label":"Company Url","value":"https://www.elevancehealth.com"},"KeyExecutives":{"label":"Key Executives","value":[{"name":"Dustin Wilcox","title":"Chief Information Security Officer"},{"name":"Gail Koziara Boudreaux","title":"President, Chief Executive Officer & Director"},{"name":"Ratnakar Lavu","title":"Chief Digital Information Officer & Executive VP"}]}},"message":null,"status":{"rCode":200,"bCodeMessage":null,"developerMessage":null}}