{"data":{"ModuleTitle":{"label":"Module Title","value":"Company Description"},"CompanyName":{"label":"Company Name","value":"ASML Holding N.V."},"Symbol":{"label":"Symbol","value":"ASML"},"Address":{"label":"Address","value":"DE RUN 6501, VELDHOVEN, 5504 DR, Netherlands"},"Phone":{"label":"Phone","value":"+31 402683000"},"Industry":{"label":"Industry","value":"Industrial Machinery/Components"},"Sector":{"label":"Sector","value":"Technology"},"Region":{"label":"Region","value":"Europe"},"CompanyDescription":{"label":"Company Description","value":"ASML Holding NV is founded in 1984 and based in the Netherlands, ASML is the leader in photolithography systems used in the manufacturing of semiconductors. Photolithography is the process in which a light source is used to expose circuit patterns from a photomask onto a semiconductor wafer. The latest technological advances in this segment allow chipmakers to continually increase the number of transistors on the same area of silicon, with lithography historically representing a meaningful portion of the cost of making cutting-edge chips. Chipmakers require next-generation EUV lithography tools from ASML to continue past the 5-nanometer process node.<br><br><table class='infobox ib-company vcard'><caption class='infobox-title fn org'></caption><tbody><tr><td colspan='2' class='infobox-image ib-company-logo logo'><span class='mw-default-size' typeof='mw:File/Frameless'><a href='/wiki/File:ASML_Holding_N.V._logo.svg' class='mw-file-description'><img src='//upload.wikimedia.org/wikipedia/en/thumb/6/6c/ASML_Holding_N.V._logo.svg/220px-ASML_Holding_N.V._logo.svg.png' decoding='async' width='220' height='62' class='mw-file-element' srcset='//upload.wikimedia.org/wikipedia/en/thumb/6/6c/ASML_Holding_N.V._logo.svg/330px-ASML_Holding_N.V._logo.svg.png 1.5x, //upload.wikimedia.org/wikipedia/en/thumb/6/6c/ASML_Holding_N.V._logo.svg/440px-ASML_Holding_N.V._logo.svg.png 2x' data-file-width='1065' data-file-height='300'></a></span></td></tr><tr><td colspan='2' class='infobox-image ib-company-logo logo'><span class='mw-default-size' typeof='mw:File/Frameless'><a href='/wiki/File:ASML_headquarters_Veldhoven.jpg' class='mw-file-description'><img src='//upload.wikimedia.org/wikipedia/commons/thumb/a/ae/ASML_headquarters_Veldhoven.jpg/250px-ASML_headquarters_Veldhoven.jpg' decoding='async' width='250' height='188' class='mw-file-element' srcset='//upload.wikimedia.org/wikipedia/commons/thumb/a/ae/ASML_headquarters_Veldhoven.jpg/375px-ASML_headquarters_Veldhoven.jpg 1.5x, //upload.wikimedia.org/wikipedia/commons/thumb/a/ae/ASML_headquarters_Veldhoven.jpg/500px-ASML_headquarters_Veldhoven.jpg 2x' data-file-width='2048' data-file-height='1536'></a></span><div class='infobox-caption'>Corporate headquarters in <a href='/wiki/Veldhoven' title='Veldhoven'>Veldhoven</a></div></td></tr><tr><th scope='row' class='infobox-label'>Company type</th><td class='infobox-data category'><a href='/wiki/Public_company' title='Public company'>Public</a></td></tr><tr><th scope='row' class='infobox-label'><div style='display: inline-block; line-height: 1.2em; padding: .1em 0;'><a href='/wiki/Ticker_symbol' title='Ticker symbol'>Traded as</a></div></th><td class='infobox-data'><style data-mw-deduplicate='TemplateStyles:r1126788409'>.mw-parser-output .plainlist ol,.mw-parser-output .plainlist ul{line-height:inherit;list-style:none;margin:0;padding:0}.mw-parser-output .plainlist ol li,.mw-parser-output .plainlist ul li{margin-bottom:0}</style><div class='plainlist'><ul><li><a href='/wiki/Euronext_Amsterdam' title='Euronext Amsterdam'>Euronext Amsterdam</a>:&nbsp;<a rel='nofollow' class='external text' href='https://euronext.com/products/equities/NL0010273215-XAMS/quotes'>ASML</a></li><li><a href='/wiki/AEX_index' title='AEX index'>AEX</a> component</li><li><a href='/wiki/Nasdaq' title='Nasdaq'>Nasdaq</a>:&nbsp;<a rel='nofollow' class='external text' href='https://www.nasdaq.com/market-activity/stocks/asml'>ASML</a></li><li><a href='/wiki/Nasdaq-100' title='Nasdaq-100'>Nasdaq-100</a> component</li></ul></div></td></tr><tr><th scope='row' class='infobox-label'>Industry</th><td class='infobox-data category'><a href='/wiki/Semiconductor_industry' title='Semiconductor industry'>Semiconductor industry</a></td></tr><tr><th scope='row' class='infobox-label'>Founded</th><td class='infobox-data'>1984 (joint venture)<br>1988 (independent company)</td></tr><tr><th scope='row' class='infobox-label'>Headquarters</th><td class='infobox-data label'><a href='/wiki/Veldhoven' title='Veldhoven'>Veldhoven</a>, Netherlands</td></tr><tr><th scope='row' class='infobox-label'><div style='display: inline-block; line-height: 1.2em; padding: .1em 0;'>Key people</div></th><td class='infobox-data agent'><link rel='mw-deduplicated-inline-style' href='mw-data:TemplateStyles:r1126788409'><div class='plainlist'><ul><li>Christophe Fouquet (<a href='/wiki/Chief_executive_officer' title='Chief executive officer'>CEO</a>)</li><li><a href='/wiki/Gerard_Kleisterlee' title='Gerard Kleisterlee'>Gerard Kleisterlee</a> (<a href='/wiki/Chairman' class='mw-redirect' title='Chairman'>chairman</a> of the <a href='/wiki/Supervisory_board' title='Supervisory board'>supervisory board</a>)</li></ul></div></td></tr><tr><th scope='row' class='infobox-label'>Products</th><td class='infobox-data'><a href='/wiki/Photolithography' title='Photolithography'>Photolithography</a> systems for the <a href='/wiki/Semiconductor' title='Semiconductor'>semiconductor</a> industry</td></tr><tr><th scope='row' class='infobox-label'>Revenue</th><td class='infobox-data'><span typeof='mw:File'><span title='Increase'><img alt='Increase' src='//upload.wikimedia.org/wikipedia/commons/thumb/b/b0/Increase2.svg/11px-Increase2.svg.png' decoding='async' width='11' height='11' class='mw-file-element' srcset='//upload.wikimedia.org/wikipedia/commons/thumb/b/b0/Increase2.svg/17px-Increase2.svg.png 1.5x, //upload.wikimedia.org/wikipedia/commons/thumb/b/b0/Increase2.svg/22px-Increase2.svg.png 2x' data-file-width='300' data-file-height='300'></span></span> <span class='nowrap'><a href='/wiki/Euro' title='Euro'>€</a>27.56 billion</span> (2023)<sup id='cite_ref-AR_1-0' class='reference'><a href='#cite_note-AR-1'><span class='cite-bracket'>[</span>1<span class='cite-bracket'>]</span></a></sup></td></tr><tr><th scope='row' class='infobox-label'><div style='display: inline-block; line-height: 1.2em; padding: .1em 0;'><a href='/wiki/Earnings_before_interest_and_taxes' title='Earnings before interest and taxes'>Operating income</a></div></th><td class='infobox-data'><span typeof='mw:File'><span title='Increase'><img alt='Increase' src='//upload.wikimedia.org/wikipedia/commons/thumb/b/b0/Increase2.svg/11px-Increase2.svg.png' decoding='async' width='11' height='11' class='mw-file-element' srcset='//upload.wikimedia.org/wikipedia/commons/thumb/b/b0/Increase2.svg/17px-Increase2.svg.png 1.5x, //upload.wikimedia.org/wikipedia/commons/thumb/b/b0/Increase2.svg/22px-Increase2.svg.png 2x' data-file-width='300' data-file-height='300'></span></span> <span class='nowrap'>€9.042 billion</span> (2023)<sup id='cite_ref-AR_1-1' class='reference'><a href='#cite_note-AR-1'><span class='cite-bracket'>[</span>1<span class='cite-bracket'>]</span></a></sup></td></tr><tr><th scope='row' class='infobox-label'><div style='display: inline-block; line-height: 1.2em; padding: .1em 0;'><a href='/wiki/Net_income' title='Net income'>Net income</a></div></th><td class='infobox-data'><span typeof='mw:File'><span title='Increase'><img alt='Increase' src='//upload.wikimedia.org/wikipedia/commons/thumb/b/b0/Increase2.svg/11px-Increase2.svg.png' decoding='async' width='11' height='11' class='mw-file-element' srcset='//upload.wikimedia.org/wikipedia/commons/thumb/b/b0/Increase2.svg/17px-Increase2.svg.png 1.5x, //upload.wikimedia.org/wikipedia/commons/thumb/b/b0/Increase2.svg/22px-Increase2.svg.png 2x' data-file-width='300' data-file-height='300'></span></span> <span class='nowrap'>€7.839 billion</span> (2023)<sup id='cite_ref-AR_1-2' class='reference'><a href='#cite_note-AR-1'><span class='cite-bracket'>[</span>1<span class='cite-bracket'>]</span></a></sup></td></tr><tr><th scope='row' class='infobox-label'><span class='nowrap'><a href='/wiki/Asset' title='Asset'>Total assets</a></span></th><td class='infobox-data'><span typeof='mw:File'><span title='Increase'><img alt='Increase' src='//upload.wikimedia.org/wikipedia/commons/thumb/b/b0/Increase2.svg/11px-Increase2.svg.png' decoding='async' width='11' height='11' class='mw-file-element' srcset='//upload.wikimedia.org/wikipedia/commons/thumb/b/b0/Increase2.svg/17px-Increase2.svg.png 1.5x, //upload.wikimedia.org/wikipedia/commons/thumb/b/b0/Increase2.svg/22px-Increase2.svg.png 2x' data-file-width='300' data-file-height='300'></span></span> <span class='nowrap'>€39.96 billion</span> (2023)<sup id='cite_ref-AR_1-3' class='reference'><a href='#cite_note-AR-1'><span class='cite-bracket'>[</span>1<span class='cite-bracket'>]</span></a></sup></td></tr><tr><th scope='row' class='infobox-label'><span class='nowrap'><a href='/wiki/Equity_(finance)' title='Equity (finance)'>Total equity</a></span></th><td class='infobox-data'><span typeof='mw:File'><span title='Increase'><img alt='Increase' src='//upload.wikimedia.org/wikipedia/commons/thumb/b/b0/Increase2.svg/11px-Increase2.svg.png' decoding='async' width='11' height='11' class='mw-file-element' srcset='//upload.wikimedia.org/wikipedia/commons/thumb/b/b0/Increase2.svg/17px-Increase2.svg.png 1.5x, //upload.wikimedia.org/wikipedia/commons/thumb/b/b0/Increase2.svg/22px-Increase2.svg.png 2x' data-file-width='300' data-file-height='300'></span></span> <span class='nowrap'>€13.45 billion</span> (2023)<sup id='cite_ref-AR_1-4' class='reference'><a href='#cite_note-AR-1'><span class='cite-bracket'>[</span>1<span class='cite-bracket'>]</span></a></sup></td></tr><tr><th scope='row' class='infobox-label'><div style='display: inline-block; line-height: 1.2em; padding: .1em 0;'>Number of employees</div></th><td class='infobox-data'>42,416 (2023)<sup id='cite_ref-AR_1-5' class='reference'><a href='#cite_note-AR-1'><span class='cite-bracket'>[</span>1<span class='cite-bracket'>]</span></a></sup></td></tr><tr><th scope='row' class='infobox-label'>Website</th><td class='infobox-data'><span class='url'><a rel='nofollow' class='external text' href='https://www.asml.com/'>asml.com</a></span></td></tr></tbody></table><br><iframe width='400' height='225' src='https://www.youtube-nocookie.com/embed/9RZreu5z_Gc?si=44AyhcHwLq2knvPC&amp;controls=0' title='YouTube video player' frameborder='0' allow='accelerometer; autoplay; clipboard-write; encrypted-media; gyroscope; picture-in-picture; web-share' referrerpolicy='strict-origin-when-cross-origin' allowfullscreen></iframe>"},"CompanyUrl":{"label":"Company Url","value":"https://www.asml.com"},"KeyExecutives":{"label":"Key Executives","value":[{"name":"Christophe D. Fouquet","title":"President & Chief Executive Officer"},{"name":"Frédéric J. M. Schneider-Maunoury","title":"Chief Operations Officer & Executive VP"}]}},"message":null,"status":{"rCode":200,"bCodeMessage":null,"developerMessage":null}}
